codenav/__init__.py
codenav/app.py
codenav/cli.py
codenav/dash_callbacks.py
codenav/dash_sweet_components.py
codenav/dash_trees.py
codenav/file_system_node.py
codenav/helper.py
codenav/queue_test.py
codenav/shell_server.py
codenav/assets/ezgif-2-c7fd154a6c.png
codenav/assets/minecraft-video-game-pc-rectangle-compass.jpg
codenav/assets/png-transparent-pokemon-go-computer-icons-compass-android-pokemon-go-compass-rim-android.png
codenav/assets/token_operator.css
codenav/dash/__init__.py
codenav/dash/dash_callbacks.py
codenav/dash/dash_sweet_components.py
codenav/dash/dash_trees.py
codenav/dash/file_system_node.py
codenav/dash/helper.py
codenav/dash/shell_server.py
codenav-0.0.3.dist-info/LICENSE.txt
codenav-0.0.3.dist-info/METADATA
codenav-0.0.3.dist-info/WHEEL
codenav-0.0.3.dist-info/entry_points.txt
codenav-0.0.3.dist-info/top_level.txt
codenav-0.0.3.dist-info/RECORD
