Metadata-Version: 2.1
Name: codenav
Version: 0.0.3
Summary: Web App for cleaning, searching, editing, and navigating Python code.
Home-page: https://github.com/jkrist2696/codenav
Author: Jason Krist
Author-email: jkrist2696@gmail.com
License: GNU GPLv3
Requires-Python: >=3.9
License-File: LICENSE.txt
Requires-Dist: cleandoc (>=0.0.3)
Requires-Dist: dash-ace (>=0.2.1)
Requires-Dist: dash-bootstrap-components (>=1.4.1)
Requires-Dist: dash-editor-components (>=0.0.2)
Requires-Dist: dash-iconify (>=0.1.2)
Requires-Dist: dash-mantine-components (>=0.12.1)
Requires-Dist: feffery-antd-components (>=0.2.9)
Requires-Dist: psutil (>=5.9.0)
Requires-Dist: snipsearch (>=0.0.2)
Requires-Dist: waitress (>=2.1.2)
